domible/__init__.py
domible/builders/__init__.py
domible/builders/elementFromObject.py
domible/builders/formBuilder.py
domible/builders/navBuilder.py
domible/builders/preformatted.py
domible/builders/tableBuilder.py
domible/elements/__init__.py
domible/elements/baseElements.py
domible/elements/forms.py
domible/elements/inline.py
domible/elements/lists.py
domible/elements/meta.py
domible/elements/roots.py
domible/elements/scripting.py
domible/elements/sectioning.py
domible/elements/tables.py
domible/scripts/__init__.py
domible/scripts/dibrowse/__init__.py
domible/scripts/dibrowse/main.py
domible/scripts/dibrowse/parsedmod.py
domible/scripts/dicli/__init__.py
domible/scripts/dicli/main.py
domible/starterDocuments/__init__.py
domible/starterDocuments/basicDocuments.py
domible/tools.py
domible/utils.py
domible-0.2.0.dist-info/entry_points.txt
domible-0.2.0.dist-info/LICENSE
domible-0.2.0.dist-info/METADATA
domible-0.2.0.dist-info/WHEEL
domible-0.2.0.dist-info/RECORD
